md_viewer_editor/__about__.py
md_viewer_editor/__init__.py
md_viewer_editor/content_switcher.tcss
md_viewer_editor/md_viewer.py
md_viewer_editor-0.0.1.dist-info/METADATA
md_viewer_editor-0.0.1.dist-info/WHEEL
md_viewer_editor-0.0.1.dist-info/entry_points.txt
md_viewer_editor-0.0.1.dist-info/RECORD
