Metadata-Version: 2.3
Name: md-viewer-editor
Version: 0.0.1
Summary: A .MD viewer and editor
Project-URL: Documentation, https://github.com/Manuel Mateo/md-viewer-editor#readme
Project-URL: Issues, https://github.com/Manuel Mateo/md-viewer-editor/issues
Project-URL: Source, https://github.com/Manuel Mateo/md-viewer-editor
Author-email: Manuel Mateo <yekayama@gmail.com>
License-Expression: MIT
Classifier: Development Status :: 4 - Beta
Classifier: Programming Language :: Python
Classifier: Programming Language :: Python :: 3.8
Classifier: Programming Language :: Python :: 3.9
Classifier: Programming Language :: Python :: 3.10
Classifier: Programming Language :: Python :: 3.11
Classifier: Programming Language :: Python :: 3.12
Classifier: Programming Language :: Python :: Implementation :: CPython
Classifier: Programming Language :: Python :: Implementation :: PyPy
Requires-Python: >=3.8
Requires-Dist: textual==0.79.1
